tests/test_bars.py
tests/test_heatmaps.py
tests/test_histograms.py
tests/test_line_charts.py
tests/test_markers.py
tests/test_polar.py
tests/test_scatter3d.py
tikzplotly/__about__.py
tikzplotly/__init__.py
tikzplotly/_annotations.py
tikzplotly/_axis.py
tikzplotly/_bar.py
tikzplotly/_color.py
tikzplotly/_dash.py
tikzplotly/_data.py
tikzplotly/_dataContainer.py
tikzplotly/_heatmap.py
tikzplotly/_histogram.py
tikzplotly/_marker.py
tikzplotly/_polar.py
tikzplotly/_save.py
tikzplotly/_scatter.py
tikzplotly/_scatter3d.py
tikzplotly/_tex.py
tikzplotly/_utils.py
tikzplotly-0.2.1.dist-info/licenses/LICENSE
tikzplotly-0.2.1.dist-info/METADATA
tikzplotly-0.2.1.dist-info/WHEEL
tikzplotly-0.2.1.dist-info/top_level.txt
tikzplotly-0.2.1.dist-info/RECORD
