Metadata-Version: 2.4
Name: tikzplotly
Version: 0.2.1
Summary: Convert plotly figures to LaTeX / TikZ figures
Author-email: Thomas Saigre <tikzplotly@outlook.fr>
License: The MIT License (MIT)
Project-URL: Code, https://github.com/thomas-saigre/tikzplotly
Project-URL: Issues, https://github.com/thomas-saigre/tikzplotly/issues
Keywords: plotly,latex,tikz,figure,conversion,graphics
Classifier: Development Status :: 5 - Production/Stable
Classifier: Programming Language :: Python
Classifier: Programming Language :: Python :: 3
Classifier: Programming Language :: Python :: 3.9
Classifier: Programming Language :: Python :: 3.10
Classifier: Programming Language :: Python :: 3.11
Classifier: Programming Language :: Python :: 3.12
Classifier: Programming Language :: Python :: 3.13
Classifier: License :: OSI Approved :: MIT License
Classifier: Operating System :: OS Independent
Classifier: Topic :: Multimedia :: Graphics :: Graphics Conversion
Classifier: Topic :: Scientific/Engineering :: Visualization
License-File: LICENSE
Requires-Dist: numpy
Requires-Dist: plotly
Requires-Dist: pillow
Provides-Extra: dev
Requires-Dist: pandas; extra == "dev"
Dynamic: license-file
